{
  "version": 1,
  "serviceConfiguration": {
    "apiName": "learnawsvue",
    "serviceName": "AppSync",
    "gqlSchemaPath": "/tmp/amplify-d23c5f9d-a939-4a91-8f99-46fa1b13c7f3/amplify/backend/api/learnawsvue/schema.graphql",
    "defaultAuthType": {
      "mode": "API_KEY",
      "keyDescription": "api key description",
      "expirationTime": 30
    },
    "additionalAuthTypes": [
      {
        "mode": "AWS_IAM"
      },
      {
        "mode": "AMAZON_COGNITO_USER_POOLS",
        "cognitoUserPoolId": "authlearnawsvue0e2c30e2"
      }
    ],
    "conflictResolution": {
      "defaultResolutionStrategy": {
        "type": "AUTOMERGE"
      }
    }
  }
}