{
  "version": 1,
  "serviceConfiguration": {
    "apiName": "learnawsvue",
    "serviceName": "AppSync",
    "gqlSchemaPath": "/tmp/amplify-f9eedf39-f1fc-4030-bc21-55fcdc8ac4f2/amplify/backend/api/learnawsvue/schema.graphql",
    "defaultAuthType": {
      "mode": "AMAZON_COGNITO_USER_POOLS",
      "cognitoUserPoolId": "authlearnawsvue0e2c30e2"
    },
    "additionalAuthTypes": [
      {
        "mode": "AWS_IAM"
      },
      {
        "mode": "API_KEY",
        "keyDescription": "api key description",
        "expirationTime": 30
      }
    ],
    "conflictResolution": {
      "defaultResolutionStrategy": {
        "type": "AUTOMERGE"
      }
    }
  }
}